Metadata-Version: 1.0
Name: lgc-basedb
Version: 1.0
Summary: aki
Home-page: https://github.com/wxnacy/wwx
Author: aki
Author-email: aki@gmail.com
License: MIT License
Keywords: aki
Platform: any
